commitizen_ros/__init__.py
commitizen_ros-0.1.0.dist-info/LICENSE
commitizen_ros-0.1.0.dist-info/METADATA
commitizen_ros-0.1.0.dist-info/WHEEL
commitizen_ros-0.1.0.dist-info/entry_points.txt
commitizen_ros-0.1.0.dist-info/top_level.txt
commitizen_ros-0.1.0.dist-info/RECORD
