Metadata-Version: 2.1
Name: commitizen_ros
Version: 0.1.0
Summary: A ROS Version Provider for Commitizen
Author-email: Michael Stinger <mvstinger@gmail.com>
Maintainer-email: Michael Stinger <mvstinger@gmail.com>
Project-URL: Homepage, https://github.com/pypa/sampleproject
Project-URL: Bug Reports, https://github.com/pypa/sampleproject/issues
Project-URL: Funding, https://donate.pypi.org
Project-URL: Say Thanks!, http://saythanks.io/to/example
Project-URL: Source, https://github.com/pypa/sampleproject/
Keywords: ROS,Commitizen,Version Provider
Classifier: Development Status :: 3 - Alpha
Classifier: Environment :: Console
Classifier: Intended Audience :: Developers
Classifier: License :: OSI Approved :: MIT License
Classifier: Programming Language :: Python :: 3
Classifier: Programming Language :: Python :: 3.4
Classifier: Programming Language :: Python :: 3.9
Classifier: Programming Language :: Python :: 3.10
Classifier: Programming Language :: Python :: 3.11
Classifier: Programming Language :: Python :: 3.12
Classifier: Programming Language :: Python :: 3.13
Classifier: Programming Language :: Python :: 3 :: Only
Classifier: Topic :: Software Development :: Build Tools
Classifier: Topic :: Software Development :: Version Control
Requires-Python: >=3.4
License-File: LICENSE
Requires-Dist: commitizen>=3.0.0
Provides-Extra: test
Requires-Dist: pytest; extra == "test"
